autocodegen/__init__.py
autocodegen/_internal/__init__.py
autocodegen/_internal/config.py
autocodegen/_internal/expand.py
autocodegen/_internal/py.typed
autocodegen/_internal/utils.py
autocodegen/py.typed
autocodegen/run.py
autocodegen/utils.py
autocodegen-0.1.0.dist-info/WHEEL
autocodegen-0.1.0.dist-info/entry_points.txt
autocodegen-0.1.0.dist-info/METADATA
autocodegen-0.1.0.dist-info/RECORD
