Metadata-Version: 2.3
Name: autocodegen
Version: 0.1.0
Summary: Library and utilities for auto-code generators
Author: ramblehead
Author-email: ramblehead <<v.rybynok@gmail.com>>
Requires-Dist: mako~=1.2.4
Requires-Dist: pydantic>=2.12.5
Requires-Python: ==3.14.*
